LICENSE.txt
MANIFEST.in
README.md
setup.cfg
setup.py
asynctnt_queue/__init__.py
asynctnt_queue/exceptions.py
asynctnt_queue/queue.py
asynctnt_queue/task.py
asynctnt_queue/tube.py
asynctnt_queue.egg-info/PKG-INFO
asynctnt_queue.egg-info/SOURCES.txt
asynctnt_queue.egg-info/dependency_links.txt
asynctnt_queue.egg-info/requires.txt
asynctnt_queue.egg-info/top_level.txt
tests/__init__.py
tests/test_queue.py
tests/test_task.py
tests/test_tube.py