Metadata-Version: 1.1
Name: asynctnt-queue
Version: 0.0.4
Summary: Tarantool Queue python/asyncio bindings
Home-page: https://github.com/igorcoding/asynctnt-queue
Author: igorcoding
Author-email: igorcoding@gmail.com
License: Apache Software License
Platform: UNKNOWN
Classifier: Programming Language :: Python :: 3 :: Only
Classifier: Programming Language :: Python :: 3.5
Classifier: Programming Language :: Python :: 3.6
Classifier: Intended Audience :: Developers
Classifier: License :: OSI Approved :: Apache Software License
Classifier: Topic :: Software Development :: Libraries :: Python Modules
Classifier: Topic :: Database :: Front-Ends
